ofunctions.file_utils-1.2.4-py3.10-nspkg.pth
ofunctions/file_utils/__init__.py
ofunctions.file_utils-1.2.4.dist-info/LICENSE
ofunctions.file_utils-1.2.4.dist-info/METADATA
ofunctions.file_utils-1.2.4.dist-info/WHEEL
ofunctions.file_utils-1.2.4.dist-info/namespace_packages.txt
ofunctions.file_utils-1.2.4.dist-info/top_level.txt
ofunctions.file_utils-1.2.4.dist-info/RECORD
