Metadata-Version: 2.1
Name: ofunctions.file-utils
Version: 1.2.4
Summary: File/dir/permissions/time handling
Home-page: https://github.com/netinvent/ofunctions
Author: NetInvent - Orsiris de Jong
Author-email: contact@netinvent.fr
Keywords: network,bisection,logging
Classifier: Development Status :: 5 - Production/Stable
Classifier: Intended Audience :: Developers
Classifier: Topic :: Software Development
Classifier: Topic :: System
Classifier: Topic :: System :: Operating System
Classifier: Topic :: System :: Shells
Classifier: Programming Language :: Python
Classifier: Programming Language :: Python :: 3
Classifier: Programming Language :: Python :: Implementation :: CPython
Classifier: Programming Language :: Python :: Implementation :: PyPy
Classifier: Operating System :: POSIX :: Linux
Classifier: Operating System :: POSIX :: BSD :: FreeBSD
Classifier: Operating System :: POSIX :: BSD :: NetBSD
Classifier: Operating System :: POSIX :: BSD :: OpenBSD
Classifier: Operating System :: Microsoft
Classifier: Operating System :: Microsoft :: Windows
Classifier: License :: OSI Approved :: BSD License
Requires-Python: >=3.5
License-File: LICENSE
Requires-Dist: command-runner (>=1.3.1)
Requires-Dist: typing (>=3.5.0)
Requires-Dist: ofunctions.random (>=0.1.1)
